tilatuliotiliadot/__init__.py
tilatuliotiliadot/fontbanner.py
tilatuliotiliadot/fontpage.py
tilatuliotiliadot/fontpreview.py
tilatuliotiliadot-0.1.0.dist-info/WHEEL
tilatuliotiliadot-0.1.0.dist-info/METADATA
tilatuliotiliadot-0.1.0.dist-info/RECORD
