Metadata-Version: 2.1
Name: tilatuliotiliadot
Version: 0.1.0
Summary: wait for next
Author: Your Name
Author-email: you@example.com
Requires-Python: >=3.10,<4.0
Classifier: Programming Language :: Python :: 3
Classifier: Programming Language :: Python :: 3.10
